telarchive/__init__.py
telarchive/aat_archive.py
telarchive/aat_archive_unittest.py
telarchive/archive_analyze.py
telarchive/archive_list.py
telarchive/archive_search.py
telarchive/basic_archive.py
telarchive/cfht_archive.py
telarchive/cfht_archive_unittest.py
telarchive/eso_archive.py
telarchive/fetchsdss.py
telarchive/fetchsdss_old.py
telarchive/fetchsdss_spectra.py
telarchive/fetchsdss_unittest.py
telarchive/gemini_archive.py
telarchive/gemini_archive_prev.py
telarchive/gemini_archive_unittest.py
telarchive/get_sdssfiles.py
telarchive/get_sdssfiles_unittest.py
telarchive/getcoords.py
telarchive/getgsc2.py
telarchive/gsc2_archive.py
telarchive/hst_archive.py
telarchive/hst_archive_unittest.py
telarchive/hst_eso_archive.py
telarchive/ing_archive_lapalma.py
telarchive/ing_archive_lapalma_unittest.py
telarchive/ing_archive_new.py
telarchive/mast_archive.py
telarchive/mast_archive_unittest.py
telarchive/module_list.py
telarchive/multipart_form.py
telarchive/noao_archive.py
telarchive/sdss_combined_archive.py
telarchive/sdss_coords_archive.py
telarchive/sdss_coords_archive2.py
telarchive/sdss_coords_archive_unittest.py
telarchive/sdss_das_archive.py
telarchive/sdss_dr12_archive.py
telarchive/sdss_dr14spec_archive.py
telarchive/sdss_dr14spec_archive_unittest.py
telarchive/sdss_sas_archive.py
telarchive/setup.py
telarchive/simbad_archive.py
telarchive/smoka_archive.py
telarchive/smoka_archive_unittest.py
telarchive/spitzer_archive.py
telarchive/spitzer_archive_unittest.py
telarchive/test_modules.py
telarchive/ukirt_archive.py
telarchive/ukirt_archive_unittest.py
telarchive/utils.py
telarchive/utils_unittest.py
telarchive/zibetti.py
telarchive-2.0.3.data/scripts/do_fetchsdss.py
telarchive-2.0.3.data/scripts/do_fetchsdss_spectra.py
telarchive-2.0.3.data/scripts/dosearch.py
telarchive-2.0.3.dist-info/DESCRIPTION.rst
telarchive-2.0.3.dist-info/METADATA
telarchive-2.0.3.dist-info/RECORD
telarchive-2.0.3.dist-info/WHEEL
telarchive-2.0.3.dist-info/metadata.json
telarchive-2.0.3.dist-info/top_level.txt
