Metadata-Version: 2.0
Name: telarchive
Version: 2.0.3
Summary: Script for automated searches of several major astronomical telescope archives
Home-page: http://www.mpe.mpg.de/~erwin/code/
Author: Peter Erwin
Author-email: erwin@mpe.mpg.de
License: GPL
Keywords: astronomy,science
Platform: UNKNOWN
Classifier: Development Status :: 5 - Production/Stable
Classifier: Programming Language :: Python :: 2
Classifier: Programming Language :: Python :: 2.7
Classifier: Programming Language :: Python :: 3
Classifier: Programming Language :: Python :: 3.5
Classifier: Programming Language :: Python :: 3.6
